{
  "id": "ab439922-dd8a-4589-aa2b-938142fb98b1",
  "prevId": "00000000-0000-0000-0000-000000000000",
  "version": "7",
  "dialect": "postgresql",
  "tables": {
    "public.attorney_connections": {
      "name": "attorney_connections",
      "schema": "",
      "columns": {
        "id": {
          "name": "id",
          "type": "serial",
          "primaryKey": true,
          "notNull": true
        },
        "user_id": {
          "name": "user_id",
          "type": "varchar",
          "primaryKey": false,
          "notNull": true
        },
        "attorney_id": {
          "name": "attorney_id",
          "type": "integer",
          "primaryKey": false,
          "notNull": true
        },
        "incident_id": {
          "name": "incident_id",
          "type": "integer",
          "primaryKey": false,
          "notNull": false
        },
        "status": {
          "name": "status",
          "type": "varchar",
          "primaryKey": false,
          "notNull": true,
          "default": "'pending'"
        },
        "message": {
          "name": "message",
          "type": "text",
          "primaryKey": false,
          "notNull": false
        },
        "created_at": {
          "name": "created_at",
          "type": "timestamp",
          "primaryKey": false,
          "notNull": false,
          "default": "now()"
        }
      },
      "indexes": {},
      "foreignKeys": {
        "attorney_connections_user_id_users_id_fk": {
          "name": "attorney_connections_user_id_users_id_fk",
          "tableFrom": "attorney_connections",
          "tableTo": "users",
          "columnsFrom": [
            "user_id"
          ],
          "columnsTo": [
            "id"
          ],
          "onDelete": "no action",
          "onUpdate": "no action"
        },
        "attorney_connections_attorney_id_attorneys_id_fk": {
          "name": "attorney_connections_attorney_id_attorneys_id_fk",
          "tableFrom": "attorney_connections",
          "tableTo": "attorneys",
          "columnsFrom": [
            "attorney_id"
          ],
          "columnsTo": [
            "id"
          ],
          "onDelete": "no action",
          "onUpdate": "no action"
        },
        "attorney_connections_incident_id_incidents_id_fk": {
          "name": "attorney_connections_incident_id_incidents_id_fk",
          "tableFrom": "attorney_connections",
          "tableTo": "incidents",
          "columnsFrom": [
            "incident_id"
          ],
          "columnsTo": [
            "id"
          ],
          "onDelete": "no action",
          "onUpdate": "no action"
        }
      },
      "compositePrimaryKeys": {},
      "uniqueConstraints": {},
      "policies": {},
      "checkConstraints": {},
      "isRLSEnabled": false
    },
    "public.attorneys": {
      "name": "attorneys",
      "schema": "",
      "columns": {
        "id": {
          "name": "id",
          "type": "serial",
          "primaryKey": true,
          "notNull": true
        },
        "user_id": {
          "name": "user_id",
          "type": "varchar",
          "primaryKey": false,
          "notNull": true
        },
        "firm_name": {
          "name": "firm_name",
          "type": "varchar",
          "primaryKey": false,
          "notNull": false
        },
        "specialties": {
          "name": "specialties",
          "type": "jsonb",
          "primaryKey": false,
          "notNull": false
        },
        "states": {
          "name": "states",
          "type": "jsonb",
          "primaryKey": false,
          "notNull": false
        },
        "rating": {
          "name": "rating",
          "type": "integer",
          "primaryKey": false,
          "notNull": false
        },
        "verified": {
          "name": "verified",
          "type": "boolean",
          "primaryKey": false,
          "notNull": false,
          "default": false
        },
        "contact_info": {
          "name": "contact_info",
          "type": "jsonb",
          "primaryKey": false,
          "notNull": false
        },
        "bio": {
          "name": "bio",
          "type": "text",
          "primaryKey": false,
          "notNull": false
        },
        "created_at": {
          "name": "created_at",
          "type": "timestamp",
          "primaryKey": false,
          "notNull": false,
          "default": "now()"
        }
      },
      "indexes": {},
      "foreignKeys": {
        "attorneys_user_id_users_id_fk": {
          "name": "attorneys_user_id_users_id_fk",
          "tableFrom": "attorneys",
          "tableTo": "users",
          "columnsFrom": [
            "user_id"
          ],
          "columnsTo": [
            "id"
          ],
          "onDelete": "no action",
          "onUpdate": "no action"
        }
      },
      "compositePrimaryKeys": {},
      "uniqueConstraints": {},
      "policies": {},
      "checkConstraints": {},
      "isRLSEnabled": false
    },
    "public.incidents": {
      "name": "incidents",
      "schema": "",
      "columns": {
        "id": {
          "name": "id",
          "type": "serial",
          "primaryKey": true,
          "notNull": true
        },
        "user_id": {
          "name": "user_id",
          "type": "varchar",
          "primaryKey": false,
          "notNull": true
        },
        "title": {
          "name": "title",
          "type": "varchar",
          "primaryKey": false,
          "notNull": true
        },
        "description": {
          "name": "description",
          "type": "text",
          "primaryKey": false,
          "notNull": false
        },
        "location": {
          "name": "location",
          "type": "jsonb",
          "primaryKey": false,
          "notNull": false
        },
        "status": {
          "name": "status",
          "type": "varchar",
          "primaryKey": false,
          "notNull": true,
          "default": "'active'"
        },
        "priority": {
          "name": "priority",
          "type": "varchar",
          "primaryKey": false,
          "notNull": true,
          "default": "'normal'"
        },
        "media_urls": {
          "name": "media_urls",
          "type": "jsonb",
          "primaryKey": false,
          "notNull": false
        },
        "cloud_backup": {
          "name": "cloud_backup",
          "type": "boolean",
          "primaryKey": false,
          "notNull": false,
          "default": false
        },
        "contacts_notified": {
          "name": "contacts_notified",
          "type": "boolean",
          "primaryKey": false,
          "notNull": false,
          "default": false
        },
        "report_generated": {
          "name": "report_generated",
          "type": "boolean",
          "primaryKey": false,
          "notNull": false,
          "default": false
        },
        "notes": {
          "name": "notes",
          "type": "text",
          "primaryKey": false,
          "notNull": false
        },
        "created_at": {
          "name": "created_at",
          "type": "timestamp",
          "primaryKey": false,
          "notNull": false,
          "default": "now()"
        },
        "updated_at": {
          "name": "updated_at",
          "type": "timestamp",
          "primaryKey": false,
          "notNull": false,
          "default": "now()"
        }
      },
      "indexes": {},
      "foreignKeys": {
        "incidents_user_id_users_id_fk": {
          "name": "incidents_user_id_users_id_fk",
          "tableFrom": "incidents",
          "tableTo": "users",
          "columnsFrom": [
            "user_id"
          ],
          "columnsTo": [
            "id"
          ],
          "onDelete": "no action",
          "onUpdate": "no action"
        }
      },
      "compositePrimaryKeys": {},
      "uniqueConstraints": {},
      "policies": {},
      "checkConstraints": {},
      "isRLSEnabled": false
    },
    "public.legal_rights": {
      "name": "legal_rights",
      "schema": "",
      "columns": {
        "id": {
          "name": "id",
          "type": "serial",
          "primaryKey": true,
          "notNull": true
        },
        "state": {
          "name": "state",
          "type": "varchar",
          "primaryKey": false,
          "notNull": true
        },
        "category": {
          "name": "category",
          "type": "varchar",
          "primaryKey": false,
          "notNull": true
        },
        "title": {
          "name": "title",
          "type": "varchar",
          "primaryKey": false,
          "notNull": true
        },
        "description": {
          "name": "description",
          "type": "text",
          "primaryKey": false,
          "notNull": true
        },
        "details": {
          "name": "details",
          "type": "text",
          "primaryKey": false,
          "notNull": false
        },
        "last_updated": {
          "name": "last_updated",
          "type": "timestamp",
          "primaryKey": false,
          "notNull": false,
          "default": "now()"
        }
      },
      "indexes": {},
      "foreignKeys": {},
      "compositePrimaryKeys": {},
      "uniqueConstraints": {},
      "policies": {},
      "checkConstraints": {},
      "isRLSEnabled": false
    },
    "public.sessions": {
      "name": "sessions",
      "schema": "",
      "columns": {
        "sid": {
          "name": "sid",
          "type": "varchar",
          "primaryKey": true,
          "notNull": true
        },
        "sess": {
          "name": "sess",
          "type": "jsonb",
          "primaryKey": false,
          "notNull": true
        },
        "expire": {
          "name": "expire",
          "type": "timestamp",
          "primaryKey": false,
          "notNull": true
        }
      },
      "indexes": {
        "IDX_session_expire": {
          "name": "IDX_session_expire",
          "columns": [
            {
              "expression": "expire",
              "isExpression": false,
              "asc": true,
              "nulls": "last"
            }
          ],
          "isUnique": false,
          "concurrently": false,
          "method": "btree",
          "with": {}
        }
      },
      "foreignKeys": {},
      "compositePrimaryKeys": {},
      "uniqueConstraints": {},
      "policies": {},
      "checkConstraints": {},
      "isRLSEnabled": false
    },
    "public.users": {
      "name": "users",
      "schema": "",
      "columns": {
        "id": {
          "name": "id",
          "type": "varchar",
          "primaryKey": true,
          "notNull": true
        },
        "email": {
          "name": "email",
          "type": "varchar",
          "primaryKey": false,
          "notNull": false
        },
        "first_name": {
          "name": "first_name",
          "type": "varchar",
          "primaryKey": false,
          "notNull": false
        },
        "last_name": {
          "name": "last_name",
          "type": "varchar",
          "primaryKey": false,
          "notNull": false
        },
        "profile_image_url": {
          "name": "profile_image_url",
          "type": "varchar",
          "primaryKey": false,
          "notNull": false
        },
        "role": {
          "name": "role",
          "type": "varchar",
          "primaryKey": false,
          "notNull": true,
          "default": "'user'"
        },
        "subscription_tier": {
          "name": "subscription_tier",
          "type": "varchar",
          "primaryKey": false,
          "notNull": true,
          "default": "'free'"
        },
        "current_state": {
          "name": "current_state",
          "type": "varchar",
          "primaryKey": false,
          "notNull": false
        },
        "preferred_language": {
          "name": "preferred_language",
          "type": "varchar",
          "primaryKey": false,
          "notNull": false,
          "default": "'en'"
        },
        "emergency_contacts": {
          "name": "emergency_contacts",
          "type": "jsonb",
          "primaryKey": false,
          "notNull": false
        },
        "created_at": {
          "name": "created_at",
          "type": "timestamp",
          "primaryKey": false,
          "notNull": false,
          "default": "now()"
        },
        "updated_at": {
          "name": "updated_at",
          "type": "timestamp",
          "primaryKey": false,
          "notNull": false,
          "default": "now()"
        }
      },
      "indexes": {},
      "foreignKeys": {},
      "compositePrimaryKeys": {},
      "uniqueConstraints": {
        "users_email_unique": {
          "name": "users_email_unique",
          "nullsNotDistinct": false,
          "columns": [
            "email"
          ]
        }
      },
      "policies": {},
      "checkConstraints": {},
      "isRLSEnabled": false
    }
  },
  "enums": {},
  "schemas": {},
  "sequences": {},
  "roles": {},
  "policies": {},
  "views": {},
  "_meta": {
    "columns": {},
    "schemas": {},
    "tables": {}
  }
}